Workbook

Sheet Read me
A1: Procure-to-pay requirements workbook
A2: Portfolio case study by Chiamaka Ikpo. Organisation anonymised; process generalised; values illustrative.
A4: Tabs
A5: Summary – requirement and test coverage, calculated with formulas from the other tabs
A6: Stakeholders – stakeholder register with interest, influence and engagement approach
A7: RACI – who is Responsible, Accountable, Consulted and Informed for each activity
A8: Requirements – traceability: pain point → requirement → user story → UAT test cases
A9: UAT Tests – test cases for user acceptance testing; update the Status column during testing
A11: How to use
A12: Blue text = cells you edit (test status, tester, date). Black text = reference content or formulas.
A13: Status values: Not run, Pass, Fail, Blocked. Summary updates automatically.

Sheet Summary
A1: Coverage summary
A3: Priority | B3: Requirements | C3: With ≥1 test | D3: Fully passed | E3: % passed
A4: Must | B4: =COUNTIF(Requirements!$D$2:$D$18,A4) -> 12 | C4: =COUNTIFS(Requirements!$D$2:$D$18,A4,Requirements!$G$2:$G$18,">0") -> 12 | D4: =SUMPRODUCT((Requirements!$D$2:$D$18=A4)*(Requirements!$G$2:$G$18>0)*(Requirements!$H$2:$H$18=Requirements!$G$2:$G$18)) -> 0 | E4: =IFERROR(D4/B4,0) -> 0
A5: Should | B5: =COUNTIF(Requirements!$D$2:$D$18,A5) -> 4 | C5: =COUNTIFS(Requirements!$D$2:$D$18,A5,Requirements!$G$2:$G$18,">0") -> 4 | D5: =SUMPRODUCT((Requirements!$D$2:$D$18=A5)*(Requirements!$G$2:$G$18>0)*(Requirements!$H$2:$H$18=Requirements!$G$2:$G$18)) -> 0 | E5: =IFERROR(D5/B5,0) -> 0
A6: Could | B6: =COUNTIF(Requirements!$D$2:$D$18,A6) -> 1 | C6: =COUNTIFS(Requirements!$D$2:$D$18,A6,Requirements!$G$2:$G$18,">0") -> 1 | D6: =SUMPRODUCT((Requirements!$D$2:$D$18=A6)*(Requirements!$G$2:$G$18>0)*(Requirements!$H$2:$H$18=Requirements!$G$2:$G$18)) -> 0 | E6: =IFERROR(D6/B6,0) -> 0
A7: Total | B7: =SUM(B4:B6) -> 17 | C7: =SUM(C4:C6) -> 17 | D7: =SUM(D4:D6) -> 0 | E7: =IFERROR(D7/B7,0) -> 0
A10: UAT status
A11: Not run | B11: =COUNTIF('UAT Tests'!$D$2:$D$20,A11) -> 19
A12: Pass | B12: =COUNTIF('UAT Tests'!$D$2:$D$20,A12) -> 0
A13: Fail | B13: =COUNTIF('UAT Tests'!$D$2:$D$20,A13) -> 0
A14: Blocked | B14: =COUNTIF('UAT Tests'!$D$2:$D$20,A14) -> 0
A15: Total test cases | B15: =SUM(B11:B14) -> 19
A17: Go-live rule: every Must requirement fully passed (E4 = 100%).
A18: =IF(E4=1,"Ready for go-live decision","Not ready: Must requirements outstanding") -> Not ready: Must requirements outstanding

Sheet Stakeholders
A1: ID | B1: Stakeholder | C1: Interest | D1: Influence | E1: Impact on them | F1: Engagement approach | G1: RACI role
A2: SH-01 | B2: Requesting departments | C2: Fast, simple way to buy what they need | D2: Medium | E2: High | F2: Keep informed; involve in UAT | G2: Requester
A3: SH-02 | B3: Procurement team | C3: Fair sourcing, controlled spend, less rework | D3: High | E3: High | F3: Manage closely; co-design | G3: Procurement
A4: SH-03 | B4: Finance / Accounts payable | C4: Invoices match POs and receipts; budget control | D4: High | E4: High | F4: Manage closely; own approval matrix and tolerances | G4: Finance
A5: SH-04 | B5: Compliance & internal audit | C5: Full audit trail, supplier due diligence (KYC) | D5: High | E5: Medium | F5: Manage closely; sign off controls | G5: Compliance
A6: SH-05 | B6: Suppliers | C6: Clear onboarding, on-time payment | D6: Low | E6: Medium | F6: Keep informed | G6: -

Sheet RACI
A1: Activity | B1: Requester | C1: Procurement | D1: Finance | E1: Compliance | G1: One 'A'?
A2: Raise requisition | B2: R/A | C2: I | D2: I | E2: - | G2: =IF(COUNTIF(B2:E2,"*A*")=1,"OK","Fix: "&COUNTIF(B2:E2,"*A*")&" A") -> OK
A3: Source & select supplier | B3: C | C3: R/A | D3: I | E3: C | G3: =IF(COUNTIF(B3:E3,"*A*")=1,"OK","Fix: "&COUNTIF(B3:E3,"*A*")&" A") -> OK
A4: Supplier due diligence | B4: - | C4: R | D4: - | E4: A | G4: =IF(COUNTIF(B4:E4,"*A*")=1,"OK","Fix: "&COUNTIF(B4:E4,"*A*")&" A") -> OK
A5: Approve PO | B5: I | C5: R | D5: A | E5: - | G5: =IF(COUNTIF(B5:E5,"*A*")=1,"OK","Fix: "&COUNTIF(B5:E5,"*A*")&" A") -> OK
A6: Confirm goods receipt | B6: R/A | C6: I | D6: I | E6: - | G6: =IF(COUNTIF(B6:E6,"*A*")=1,"OK","Fix: "&COUNTIF(B6:E6,"*A*")&" A") -> OK
A7: Match & pay invoice | B7: - | C7: C | D7: R/A | E7: - | G7: =IF(COUNTIF(B7:E7,"*A*")=1,"OK","Fix: "&COUNTIF(B7:E7,"*A*")&" A") -> OK
A9: Check: exactly one Accountable per activity

Sheet UAT Tests
A1: Test ID | B1: Story | C1: Acceptance criterion (expected result) | D1: Status | E1: Tester | F1: Date
A2: TC-01 | B2: US-01 | C2: Given a required field is empty, when I try to submit, then the form blocks submission and highlights the field. | D2: Not run
A3: TC-02 | B3: US-01 | C3: Given I have selected a cost centre, then only budget codes valid for that cost centre are shown. | D3: Not run
A4: TC-03 | B4: US-02 | C4: Given a requisition exceeds an approval threshold, when it is approved at one level, then it routes to the next level automatically. | D4: Not run
A5: TC-04 | B5: US-02 | C5: Every approval records the approver, timestamp and decision. | D5: Not run
A6: TC-05 | B6: US-03 | C6: Given a supplier's status is Pending, when a PO is raised for that supplier, then the system blocks it and shows which documents are missing. | D6: Not run
A7: TC-06 | B7: US-04 | C7: Given the invoice, PO and receipt match within tolerance, then the invoice is marked ready for payment. | D7: Not run
A8: TC-07 | B8: US-04 | C8: Given a mismatch, then the invoice goes to the exception queue with the reason. | D8: Not run
A9: TC-08 | B9: US-05 | C9: Given a new supplier, then all checklist documents must be uploaded before status can be set to Verified. | D9: Not run
A10: TC-09 | B10: US-05 | C10: Given a document expires in 30 days, then compliance receives a notification. | D10: Not run
A11: TC-10 | B11: US-06 | C11: Given a requisition assigned to me, when I open it, then I see the cost centre, budget remaining and request value. | D11: Not run
A12: TC-11 | B12: US-06 | C12: Given approving would exceed budget, then I must enter a reason to approve. | D12: Not run
A13: TC-12 | B13: US-07 | C13: Given any requisition, PO or invoice, then I can view every action with user, timestamp and before/after values. | D13: Not run
... A20: TC-19 | B20: US-12 | C20: Given I created a supplier, then I cannot approve payments to that supplier. | D20: Not run

Sheet Requirements
A1: ID | B1: Type | C1: Requirement | D1: Priority (MoSCoW) | E1: Pain point | F1: User stories | G1: UAT tests | H1: Tests passed
A2: BR-01 | B2: Business | C2: Every purchase must be traceable from request to payment, including who approved it and when. | D2: Must | E2: P-02, P-03 | F2: US-02, US-07 | G2: =COUNTIF('UAT Tests'!$B$2:$B$20,"US-02")+COUNTIF('UAT Tests'!$B$2:$B$20,"US-07") -> 4 | H2: =COUNTIFS('UAT Tests'!$B$2:$B$20,"US-02",'UAT Tests'!$D$2:$D$20,"Pass")+COUNTIFS('UAT Tests'!$B$2:$B$20,"US-07",'UAT Tests'!$D$2:$D$20,"Pass") -> 0
A3: BR-02 | B3: Business | C3: No purchase order may be issued to a supplier whose due diligence is not verified. | D3: Must | E3: P-03 | F3: US-03, US-05 | G3: =COUNTIF('UAT Tests'!$B$2:$B$20,"US-03")+COUNTIF('UAT Tests'!$B$2:$B$20,"US-05") -> 3 | H3: =COUNTIFS('UAT Tests'!$B$2:$B$20,"US-03",'UAT Tests'!$D$2:$D$20,"Pass")+COUNTIFS('UAT Tests'!$B$2:$B$20,"US-05",'UAT Tests'!$D$2:$D$20,"Pass") -> 0
A4: BR-03 | B4: Business | C4: Invoices that match the PO and goods receipt within tolerance are paid without manual checking. | D4: Must | E4: P-04 | F4: US-04 | G4: =COUNTIF('UAT Tests'!$B$2:$B$20,"US-04") -> 2 | H4: =COUNTIFS('UAT Tests'!$B$2:$B$20,"US-04",'UAT Tests'!$D$2:$D$20,"Pass") -> 0
A5: FR-01 | B5: Functional | C5: The requisition form enforces mandatory fields (item description, quantity, estimated value, cost centre, budget code, need-by date, spend category) and blocks submission until they are complete. | D5: Must | E5: P-01 | F5: US-01 | G5: =COUNTIF('UAT Tests'!$B$2:$B$20,"US-01") -> 2 | H5: =COUNTIFS('UAT Tests'!$B$2:$B$20,"US-01",'UAT Tests'!$D$2:$D$20,"Pass") -> 0
A6: FR-02 | B6: Functional | C6: After a cost centre is selected, only budget codes valid for that cost centre are offered. | D6: Must | E6: P-01 | F6: US-01 | G6: =COUNTIF('UAT Tests'!$B$2:$B$20,"US-01") -> 2 | H6: =COUNTIFS('UAT Tests'!$B$2:$B$20,"US-01",'UAT Tests'!$D$2:$D$20,"Pass") -> 0
A7: FR-03 | B7: Functional | C7: The system routes each requisition to approvers using the approval matrix (value threshold and spend category). | D7: Must | E7: P-02 | F7: US-02 | G7: =COUNTIF('UAT Tests'!$B$2:$B$20,"US-02") -> 2 | H7: =COUNTIFS('UAT Tests'!$B$2:$B$20,"US-02",'UAT Tests'!$D$2:$D$20,"Pass") -> 0
A8: FR-04 | B8: Functional | C8: Approvers see remaining budget for the cost centre alongside the request value. | D8: Should | E8: P-02 | F8: US-06 | G8: =COUNTIF('UAT Tests'!$B$2:$B$20,"US-06") -> 2 | H8: =COUNTIFS('UAT Tests'!$B$2:$B$20,"US-06",'UAT Tests'!$D$2:$D$20,"Pass") -> 0
A9: FR-05 | B9: Functional | C9: Approval requests not actioned within 2 working days are escalated to the approver's delegate. | D9: Should | E9: P-02 | F9: US-08 | G9: =COUNTIF('UAT Tests'!$B$2:$B$20,"US-08") -> 1 | H9: =COUNTIFS('UAT Tests'!$B$2:$B$20,"US-08",'UAT Tests'!$D$2:$D$20,"Pass") -> 0
A10: FR-06 | B10: Functional | C10: Supplier status (Pending, Verified, Expired, Blocked) is held on the supplier record; a PO cannot be issued unless status is Verified. | D10: Must | E10: P-03 | F10: US-03 | G10: =COUNTIF('UAT Tests'!$B$2:$B$20,"US-03") -> 1 | H10: =COUNTIFS('UAT Tests'!$B$2:$B$20,"US-03",'UAT Tests'!$D$2:$D$20,"Pass") -> 0
A11: FR-07 | B11: Functional | C11: Supplier onboarding uses a standard document checklist; compliance is notified 30 days before any document expires. | D11: Should | E11: P-03 | F11: US-05 | G11: =COUNTIF('UAT Tests'!$B$2:$B$20,"US-05") -> 2 | H11: =COUNTIFS('UAT Tests'!$B$2:$B$20,"US-05",'UAT Tests'!$D$2:$D$20,"Pass") -> 0
A12: FR-08 | B12: Functional | C12: Requesters confirm goods or service receipt in the system against the PO. | D12: Must | E12: P-04 | F12: US-09 | G12: =COUNTIF('UAT Tests'!$B$2:$B$20,"US-09") -> 1 | H12: =COUNTIFS('UAT Tests'!$B$2:$B$20,"US-09",'UAT Tests'!$D$2:$D$20,"Pass") -> 0
A13: FR-09 | B13: Functional | C13: The system matches invoice, PO and goods receipt on quantity and price; matches within tolerance are marked ready for payment, mismatches go to an exception queue with the reason. | D13: Must | E13: P-04 | F13: US-04 | G13: =COUNTIF('UAT Tests'!$B$2:$B$20,"US-04") -> 2 | H13: =COUNTIFS('UAT Tests'!$B$2:$B$20,"US-04",'UAT Tests'!$D$2:$D$20,"Pass") -> 0
A14: FR-10 | B14: Functional | C14: Requesters can see the status of their requisition at each stage. | D14: Could | E14: P-01 | F14: US-10 | G14: =COUNTIF('UAT Tests'!$B$2:$B$20,"US-10") -> 1 | H14: =COUNTIFS('UAT Tests'!$B$2:$B$20,"US-10",'UAT Tests'!$D$2:$D$20,"Pass") -> 0
A15: FR-11 | B15: Functional | C15: A monthly report shows cycle time, first-time-complete rate, match rate and spend with unverified suppliers. | D15: Should | E15: All | F15: US-11 | G15: =COUNTIF('UAT Tests'!$B$2:$B$20,"US-11") -> 1 | H15: =COUNTIFS('UAT Tests'!$B$2:$B$20,"US-11",'UAT Tests'!$D$2:$D$20,"Pass") -> 0
A16: NFR-01 | B16: Non-functional | C16: Every create, approve, reject, change and payment action is logged with user, timestamp and before/after values; the log cannot be edited. | D16: Must | E16: P-02 | F16: US-07 | G16: =COUNTIF('UAT Tests'!$B$2:$B$20,"US-07") -> 2 | H16: =COUNTIFS('UAT Tests'!$B$2:$B$20,"US-07",'UAT Tests'!$D$2:$D$20,"Pass") -> 0
A17: NFR-02 | B17: Non-functional | C17: Role-based access; segregation of duties so the same person cannot raise and approve a requisition, or create a supplier and approve a payment to it. | D17: Must | E17: P-02, P-03 | F17: US-12 | G17: =COUNTIF('UAT Tests'!$B$2:$B$20,"US-12") -> 2 | H17: =COUNTIFS('UAT Tests'!$B$2:$B$20,"US-12",'UAT Tests'!$D$2:$D$20,"Pass") -> 0
A18: NFR-03 | B18: Non-functional | C18: Audit records are retained for the period required by the bank's record-retention policy. | D18: Must | E18: P-03 | F18: US-07 | G18: =COUNTIF('UAT Tests'!$B$2:$B$20,"US-07") -> 2 | H18: =COUNTIFS('UAT Tests'!$B$2:$B$20,"US-07",'UAT Tests'!$D$2:$D$20,"Pass") -> 0
